batchrun/__init__.py
batchrun/cli.py
batchrun/spec.py
batchrun-0.0.14.dist-info/METADATA
batchrun-0.0.14.dist-info/WHEEL
batchrun-0.0.14.dist-info/entry_points.txt
batchrun-0.0.14.dist-info/RECORD
