Metadata-Version: 2.1
Name: batchrun
Version: 0.0.14
Summary: A simple workflow for executing scripts in parallel with varying argument values
License: MIT
Author: Bogdan Kulynych
Author-email: bogdan@kulyny.ch
Requires-Python: >=3.10,<4.0
Classifier: License :: OSI Approved :: MIT License
Classifier: Programming Language :: Python :: 3
Classifier: Programming Language :: Python :: 3.10
Classifier: Programming Language :: Python :: 3.11
Classifier: Programming Language :: Python :: 3.12
Requires-Dist: PyYAML (>=6.0.0)
Requires-Dist: click (>=8.1.3)
Requires-Dist: joblib (>=1.1.0)
Requires-Dist: rich (==13.0.0)
